i3geoweather/__init__.py
i3geoweather/daemon.py
i3geoweather/i3geoweather.py
i3geoweather-1.1.2.dist-info/LICENSE
i3geoweather-1.1.2.dist-info/METADATA
i3geoweather-1.1.2.dist-info/WHEEL
i3geoweather-1.1.2.dist-info/entry_points.txt
i3geoweather-1.1.2.dist-info/pbr.json
i3geoweather-1.1.2.dist-info/top_level.txt
i3geoweather-1.1.2.dist-info/RECORD
