Metadata-Version: 2.1
Name: i3geoweather
Version: 1.1.2
Summary: Provide temperature information to i3blocks based on geolocated IP address 
Home-page: https://github.com/joergdietrich/i3geoweather
Author: Jörg Dietrich
Author-email: joerg@joergdietrich.com
License: MIT
Keywords: i3 i3wm i3blocks i3blocks-scripts weather-app geolocation weather
Platform: UNKNOWN
Classifier: Development Status :: 5 - Production/Stable
Classifier: Intended Audience :: End Users/Desktop
Classifier: Topic :: Utilities
Classifier: License :: OSI Approved :: MIT License
Classifier: Programming Language :: Python :: 3
Requires-Dist: requests
